mina/__init__.py
mina/commands/__init__.py
mina/commands/build.py
mina/commands/list.py
mina/plugin.py
pdm_mina-0.3.2.dist-info/METADATA
pdm_mina-0.3.2.dist-info/WHEEL
pdm_mina-0.3.2.dist-info/entry_points.txt
pdm_mina-0.3.2.dist-info/RECORD
