Metadata-Version: 2.1
Name: pdm-mina
Version: 0.3.2
Author-Email: GreyElaina <GreyElaina@outlook.com>
License: MIT
Requires-Python: >=3.9
